sesamo/__init__.py
sesamo/action.py
sesamo/loss.py
sesamo/utils.py
sesamo/models/__init__.py
sesamo/models/canonicalization.py
sesamo/models/flow.py
sesamo/models/priors.py
sesamo/models/realnvp.py
sesamo/models/regularization.py
sesamo/models/scaling.py
sesamo/models/stochmod.py
sesamo/models/vmonf.py
sesamo-0.1.0.dist-info/licenses/LICENSE
sesamo-0.1.0.dist-info/METADATA
sesamo-0.1.0.dist-info/WHEEL
sesamo-0.1.0.dist-info/top_level.txt
sesamo-0.1.0.dist-info/RECORD
