Metadata-Version: 2.4
Name: sesamo
Version: 0.1.0
Summary: SESaMo provides an extension to Normalizing Flows that enforces symmetries to the output distribution.
Author-email: Janik Kreit <jkreit@uni-bonn.de>
License: MIT License
Project-URL: Homepage, https://github.com/janikkreit/SESaMo
Requires-Python: >=3.9
License-File: LICENSE
Requires-Dist: torch>=0.4.1
Requires-Dist: numpy
Requires-Dist: tqdm
Requires-Dist: matplotlib
Requires-Dist: tensorboard
Requires-Dist: hydra-core
Requires-Dist: hydra-submitit-launcher
Requires-Dist: nflows
Dynamic: license-file
